<?xml version="1.0" encoding="UTF-8"?>

<!--
  Licensed Materials - Property of IBM
 
  Copyright IBM Corporation 2012. All Rights Reserved.

  US Government Users Restricted Rights - Use, duplication or disclosure 
  restricted by GSA ADP Schedule Contract with IBM Corp.
-->
<!-- 
Copyright 2003-2005, 2010-2011  Curam Software Ltd.
All rights reserved.

This software is the confidential and proprietary information of Curam
Software, Ltd. ("Confidential Information").  You shall not
disclose such Confidential Information and shall use it only in accordance
with the terms of the license agreement you entered into with Curam Software.
-->
<messages package="curam.message"> 
  <message name="ERR_ACTIVITY_FV_DURATION"> 
    <locale language="fr">Une activité récurrente ne peut durer plus d'un jour.</locale> 
  </message>  
  <message name="ERR_ACTIVITY_FV_END_EMPTY"> 
    <locale language="fr">Saisissez la date et l'heure de fin.</locale> 
  </message>  
  <message name="ERR_ACTIVITY_FV_PRIORITY_EMPTY"> 
    <locale language="fr">Vous devez entrer la priorité.</locale> 
  </message>  
  <message name="ERR_ACTIVITY_FV_START_EMPTY"> 
    <locale language="fr">Saisissez la date et l'heure de début.</locale> 
  </message>  
  <message name="ERR_ACTIVITY_FV_SUBJECT_EMPTY"> 
    <locale language="fr">L'objet doit être saisi.</locale> 
  </message>  
  <message name="ERR_ACTIVITY_FV_TIME_STATUS_EMPTY"> 
    <locale language="fr">Saisissez le statut du temps.</locale> 
  </message>  
  <message name="ERR_ACTIVITY_FV_TYPE_EMPTY"> 
    <locale language="fr">Saisissez le type d'activité.</locale> 
  </message>  
  <message name="ERR_ACTIVITY_XFV_EMPTY"> 
    <locale language="fr">Saisissez soit un utilisateur, soit une organisation pour une activité.</locale> 
  </message>  
  <message name="ERR_ACTIVITY_XFV_END_DATE_TIME"> 
    <locale language="fr">Les date/heure de fin de l'activité ne peuvent pas être antérieures à ses date/heure de début.</locale> 
  </message>  
  <message name="ERR_ACTIVITY_XFV_LOCATION"> 
    <locale language="fr">Saisissez un identifiant d'emplacement ou un nom d'emplacement.</locale> 
  </message>  
  <message name="ERR_ACTIVITY_XRV_USERNOTINVITED"> 
    <locale language="fr">%1s n'a pas été invité à participer à cette activité.</locale> 
  </message>  
  <message name="ERR_ACTIVITY_FV_FREQUENCY_PATTERN"> 
    <locale language="fr">Saisissez le modèle de fréquence.</locale> 
  </message>  
  <!-- BEGIN, CR00225987, GSP -->  
  <message name="ERR_ACTIVITY_MAINTAIN_RIGHTS"> 
    <locale language="fr">Vous ne disposez pas des droits d'entretien pour cette activité. Contactez votre administrateur de sécurité.</locale> 
  </message>  
  <!-- END, CR00225987 -->  
  <!-- BEGIN, CR00279175, MV -->  
  <message name="ERR_ACTIVITY_VIEW_RIGHTS"> 
    <locale language="fr">Vous ne disposez pas des droits d'affichage pour cette activité. Contactez votre administrateur de sécurité.</locale> 
  </message>  
  <!-- END, CR00279175 --> 
</messages>
