<?xml version="1.0" encoding="UTF-8"?>

<!--
  Licensed Materials - Property of IBM
 
  Copyright IBM Corporation 2012. All Rights Reserved.

  US Government Users Restricted Rights - Use, duplication or disclosure 
  restricted by GSA ADP Schedule Contract with IBM Corp.
-->
<!-- 
Copyright 2003-2005 Curam Software Ltd.
All rights reserved.

This software is the confidential and proprietary information of Curam
Software, Ltd. ("Confidential Information").  You shall not
disclose such Confidential Information and shall use it only in accordance
with the terms of the license agreement you entered into with Curam Software.
-->
<messages package="curam.message"> 
  <message name="ERR_CURRENCYEXCHANGE_XFV_FROM_DATE_TO_DATE"> 
    <locale language="fr">La date de début est supérieure à la date de fin. Vérifiez que la date de début est antérieure à la date de fin.</locale> 
  </message>  
  <message name="ERR_PUBLICOFFICE_XRV_CONCERN_PREFERRED"> 
    <locale language="fr">Impossible d'annuler un bureau public s'il s'agit du bureau favori d'un rôle concerné.</locale> 
  </message>  
  <message name="ERR_PUBLICOFFICE_XRV_NOMINEES_PREFERRED"> 
    <locale language="fr">Impossible d'annuler un bureau public s'il s'agit du bureau favori d'un candidat.</locale> 
  </message>  
  <message name="ERR_PUBLICOFFICE_XRV_CONCERN"> 
    <locale language="fr">Impossible de fermer un bureau public s'il s'agit du bureau favori d'un rôle concerné.</locale> 
  </message>  
  <message name="ERR_PUBLICOFFICE_XRV_NOMINEES"> 
    <locale language="fr">Impossible de fermer un bureau public s'il s'agit du bureau favori d'un candidat.</locale> 
  </message> 
</messages>
