<?xml version="1.0" encoding="UTF-8"?>

<!--
  Licensed Materials - Property of IBM
 
  Copyright IBM Corporation 2008, 2014. All Rights Reserved.

  US Government Users Restricted Rights - Use, duplication or disclosure 
  restricted by GSA ADP Schedule Contract with IBM Corp.
-->
<!-- 
Copyright 2008,2010 Curam Software Ltd.
All rights reserved.

This software is the confidential and proprietary information of Curam
Software, Ltd. ("Confidential Information").  You shall not
disclose such Confidential Information and shall use it only in accordance
with the terms of the license agreement you entered into with Curam Software.
-->
<messages package="curam.message"> 
  <message name="ERR_INVCONF_FV_HOMEPAGE_IDENTIFIER_MUST_BE_ENTERED"> 
    <locale language="fr">L'identificateur de page d'accueil doit être saisi.</locale> 
  </message>  
  <message name="ERR_INVCONF_XFV_MODIFY_TYPE"> 
    <locale language="fr">Le type ne peut pas être modifié.</locale> 
  </message>  
  <message name="ERR_INVCONF_XRV_OVERLAPPING_INVESTIGATION"> 
    <locale language="fr">Une investigation active du même type existe déjà avec des dates de début et de fin qui se chevauchent.</locale> 
  </message>  
  <message name="INF_INVESTIGATIONCASE_CONTEXT_DESCRIPTION"> 
    <locale language="fr">%1s</locale> 
  </message>  
  <message name="ERR_INVCONF_XRV_ALREADY_DELETED"> 
    <locale language="fr">Cette investigation a déjà été supprimée.</locale> 
  </message>  
  <message name="INF_NO_MILESTONES_CONFIGURED"> 
    <locale language="fr">Aucun jalon n'a été défini pour le type d'investigation sélectionné. Veuillez contacter votre administrateur.</locale> 
  </message>  
  <!-- BEGIN, CR00409298, SS -->  
  <message name="INF_CREATED_BY_TEXT"> 
    <locale language="fr">Créé par</locale> 
  </message>  
  <message name="INF_ON_TEXT"> 
    <locale language="fr">Activé</locale>  
    <!-- END, CR00409298 --> 
  </message> 
</messages>
