<?xml version="1.0" encoding="UTF-8"?>
<!--
  Licensed Materials - Property of IBM
 
  Copyright IBM Corporation 2012. All Rights Reserved.

  US Government Users Restricted Rights - Use, duplication or disclosure 
  restricted by GSA ADP Schedule Contract with IBM Corp.
-->
<!--
Copyright 2010-2011 Curam Software Ltd.
All rights reserved.
This software is the confidential and proprietary information of Curam
Software, Ltd. (&quot;Confidential Information&quot;).  You shall not
disclose such Confidential Information and shall use it only in accordance
with the terms of the license agreement you entered into with Curam Software.
-->
<messages package="curam.creoleprogramrecommendation.facade.message">
  <message name="INF_SIMULATED_DETERMINATION_ELIGIBILITY_PERIOD">
    <locale language="en">%1d to %2d</locale>
  </message>
  <message name="INF_SIMULATED_DETERMINATION_COVERAGE_PERIOD">
    <locale language="en">%1d to %2d</locale>
  </message>
  <message name="ERR_FV_NO_PROGRAMS_SELECTED">
    <locale language="en">A check box must be selected. Please select an individual program or a combination of individual programs.</locale>
  </message>
  <message name="ERR_XRV_SIMULATED_DETERMINATION_AUTHORIZED">
    <locale language="en">This program recommendation result has been authorized.</locale>
  </message>
  <message name="ERR_XRV_SIMULATED_DETERMINATION_DECLINED">
    <locale language="en">This program recommendation result has been declined.</locale>
  </message>
  <message name="ERR_DECISION_DETAILS_CANNOT_BE_DISPLAYED">
    <locale language="en">Decision details cannot be displayed.</locale>
  </message>
  <message name="ERR_FV_APPLICATION_MANDATORY">
    <locale language="en">An application must be provided.</locale>
  </message>
  <message name="INF_INELIGIBLE_FOR_ALLPROGRAMS">
    <locale language="en">Ineligible for all programs checked.</locale>
  </message>
  <message name="ERR_ELIGIBILITY_CHECK_ALREADY_IN_PROGRESS">
    <locale language="en">There is an eligibility check already in progress.</locale>
  </message>
  <message name="INF_EIGIBILITY_CHECK_ERROR">
    <locale language="en">An error occurred during the eligibility check. Please contact your administrator.</locale>
  </message>
</messages>
