<?xml version="1.0" encoding="UTF-8"?>
<!-- 
Copyright 2009 Curam Software Ltd.
All rights reserved.

This software is the confidential and proprietary information of Curam
Software, Ltd. ("Confidential Information").  You shall not
disclose such Confidential Information and shall use it only in accordance
with the terms of the license agreement you entered into with Curam Software.
-->
<messages package="curam.message">
  <message name="ERR_RV_MUST_ENTER_PAGE_ID">
    <locale language="en">You must specify UIM Page ID.</locale>
  </message>
  <message name="ERR_RV_DUPLICATE_RECORD_USER_HOME_PAGE">
    <locale language="en">A User Homepage configuration already exists for the page '%1s' and security role '%2s'.</locale>
  </message>
  <message name="ERR_RV_DUPLICATE_RECORD_USER_HOME_PAGE_NO_SECURITY">
    <locale language="en">A User Homepage configuration already exists for the page '%1s' with no security role.</locale>
  </message>
  <message name="ERR_RV_DUPLICATE_RECORD_CUSTOMIZABLE_PAGE">
    <locale language="en">A configuration already exists for the page '%1s'.</locale>
  </message>
  <message name="ERR_GEN_PROCESS_FAILED">
    <locale language="en">An error occurred during the setup process. Please contact you administrator.</locale>
  </message>
  <message name="ERR_NUM_COLUMNS_FORMAT_EXCEPTION">
    <locale language="en">The number of columns must be specified using a number value.</locale>
  </message>
  <message name="ERR_NUM_COLUMNS_MUST_BE_GREATER_THAN_ZERO">
    <locale language="en">The number of columns must greater than zero.</locale>
  </message>
  <message name="ERR_COLUMN_WIDTH_NUMBER_FORMAT_EXCEPTION">
    <locale language="en">The column widths must be specified using a number value between 1 and 100.</locale>
  </message>
  <message name="ERR_COLUMN_WIDTH_TOTAL_SIZE_NOT_100">
    <locale language="en">The total of all column widths must be 100.</locale>
  </message>
  <message name="ERR_MIN_COLUMN_WIDTH">
    <locale language="en">The minimum column width is '%1d'.</locale>
  </message>
  <message name="ERR_NO_PODS_SELECTED">
    <locale language="en">You must select a minimum of 1 Pod to make available to the page.</locale>
  </message>
</messages>