<?xml version="1.0" encoding="UTF-8"?>
<!--
  Licensed Materials - Property of IBM
 
  Copyright IBM Corporation 2012. All Rights Reserved.

  US Government Users Restricted Rights - Use, duplication or disclosure 
  restricted by GSA ADP Schedule Contract with IBM Corp.
-->
<nc:node-config
  xmlns:nc="http://www.curamsoftware.com/curam/jde/client/widget/nc">
  
  
  <nc:node-info name="SubRuleSetTree">
    
    <nc:node-types>
      
      <nc:node-type
        icon="../Images/rules_set_16x16.gif"
        name="subRuleSet"
        >
        <nc:actions>
          <nc:action name="view">
            <nc:open-page-action page-id="RulesEditor_viewSubRuleSet">
              <nc:set-page-param
                from-key="ruleSetID"
                name="ruleSetID"
              />
            </nc:open-page-action>
          </nc:action>
        </nc:actions>
      </nc:node-type>
      
      
      <nc:node-type
        icon="../Images/objective_group_16x16.gif"
        name="objectiveGroup"
        >
        <nc:actions>
          <nc:action name="view">
            <nc:open-page-action page-id="RulesEditor_viewObjectiveGroup">
              <nc:set-page-param
                from-key="ruleSetID"
                name="ruleSetID"
              />
              <nc:set-page-param
                from-key="nodeID"
                name="nodeID" 
              /> 
            </nc:open-page-action>
          </nc:action>
        </nc:actions>
      </nc:node-type>
      
      
      <nc:node-type
        icon="../Images/objective-list-group.gif"
        name="objectiveListGroup"
        >
        <nc:actions>
          <nc:action name="view">
            <nc:open-page-action page-id="RulesEditor_viewObjectiveListGroup">
              <nc:set-page-param
                from-key="ruleSetID"
                name="ruleSetID"
              />
              <nc:set-page-param
                from-key="nodeID"
                name="nodeID" 
              /> 
            </nc:open-page-action>
          </nc:action>
        </nc:actions>
      </nc:node-type>
      
      
      <nc:node-type
        icon="../Images/objective_16x16.gif"
        name="objective"
        >
        <nc:actions>
          <nc:action name="view">
            <nc:open-page-action page-id="RulesEditor_viewObjective">
              <nc:set-page-param
                from-key="ruleSetID"
                name="ruleSetID"
              />
              <nc:set-page-param
                from-key="nodeID"
                name="nodeID" 
              /> 
            </nc:open-page-action>
          </nc:action>
        </nc:actions>
      </nc:node-type>
      
      
      <nc:node-type
        icon="../Images/rule_group_16x16.gif"
        name="ruleGroup"
        >
        <nc:actions>
          <nc:action name="view">
            <nc:open-page-action page-id="RulesEditor_viewRuleGroup">
              <nc:set-page-param
                from-key="ruleSetID"
                name="ruleSetID"
              />
              <nc:set-page-param
                from-key="nodeID"
                name="nodeID"
              />
            </nc:open-page-action>
          </nc:action>
        </nc:actions>
      </nc:node-type>
      
      
      <nc:node-type
        icon="../Images/rule_list_group_16x16.gif"
        name="ruleListGroup"
        >
        <nc:actions>
          <nc:action name="view">
            <nc:open-page-action page-id="RulesEditor_viewRuleListGroup">
              <nc:set-page-param
                from-key="ruleSetID"
                name="ruleSetID"
              />
              <nc:set-page-param
                from-key="nodeID"
                name="nodeID"
              /> 
            </nc:open-page-action>
          </nc:action>
        </nc:actions>
      </nc:node-type>
      
      
      <nc:node-type
        icon="../Images/rules_16x16.gif"
        name="rule"
        >
        <nc:actions>
          <nc:action name="view">
            <nc:open-page-action page-id="RulesEditor_viewRule">
              <nc:set-page-param
                from-key="ruleSetID"
                name="ruleSetID"
              />
              <nc:set-page-param
                from-key="nodeID"
                name="nodeID"
              /> 
            </nc:open-page-action>
          </nc:action>
        </nc:actions>
      </nc:node-type>  
      
      
      <nc:node-type
        icon="../Images/add_data_item_assignment_16.gif"
        name="dataItemAssignment"
        >
        <nc:actions>
          <nc:action name="view">
            <nc:open-page-action page-id="RulesEditor_viewDataItemAssignment">
              <nc:set-page-param
                from-key="ruleSetID"
                name="ruleSetID"
              />
              <nc:set-page-param
                from-key="nodeID"
                name="nodeID"
              /> 
            </nc:open-page-action>
          </nc:action>
        </nc:actions>
      </nc:node-type>
      
      <nc:node-type
        icon="../Images/add_subrule_set_16x16.gif"
        name="subRuleSetLink"
        >
        <nc:actions>
          <nc:action name="view">
            <nc:open-page-action page-id="RulesEditor_viewSubRuleSetLink">
              <nc:set-page-param
                from-key="ruleSetID"
                name="ruleSetID"
              />
              <nc:set-page-param
                from-key="nodeID"
                name="nodeID"
              /> 
            </nc:open-page-action>
          </nc:action>
        </nc:actions>
      </nc:node-type>
      
    </nc:node-types>
  </nc:node-info>
</nc:node-config>