<?xml version="1.0" encoding="UTF-8"?>

<!--
  Licensed Materials - Property of IBM
 
  Copyright IBM Corporation 2009, 2014. All Rights Reserved.

  US Government Users Restricted Rights - Use, duplication or disclosure 
  restricted by GSA ADP Schedule Contract with IBM Corp.
-->
<!-- 
Copyright 2009 Curam Software Ltd.
All rights reserved.
This software is the confidential and proprietary information of Curam
Software, Ltd. ("Confidential Information").  You shall not
disclose such Confidential Information and shall use it only in accordance
with the terms of the license agreement you entered into with Curam Software.
-->
<messages package="curam.dynamicevidence.message"> 
  <message name="ERR_START_DATE_DOB"> 
    <locale language="fr">La '%1s' doit être postérieure à la date de naissance du participant. La date de naissance du participant est le '%2d'.</locale> 
  </message>  
  <message name="ERR_EVIDENCE_PARTICIPANT_EXISTS"> 
    <locale language="fr">Cette %1c existe déjà pour ce participant.</locale> 
  </message>  
  <message name="ERR_ALTID_MUST_NOT_BE_ENTERED"> 
    <locale language="fr">L'ID alternatif ne doit pas être spécifié lorsque la personne est déjà enregistrée dans le système.</locale> 
  </message>  
  <message name="ERR_DOB_MUST_NOT_BE_ENTERED"> 
    <locale language="fr">La date de naissance doit être spécifiée lorsque la personne est déjà enregistrée dans le système.</locale> 
  </message>  
  <message name="ERR_GENDER_MUST_NOT_BE_ENTERED"> 
    <locale language="fr">Le sexe ne doit pas être spécifié lorsque la personne est déjà enregistrée dans le système.</locale> 
  </message>  
  <message name="RUN_VALIDATIONMODE_UNKNOWN"> 
    <locale language="fr">Un mode de validation inconnu est spécifié avec les détails suivants, '%1s'.</locale> 
  </message>  
  <!-- Start,DependentValidator -->  
  <message name="ERR_ATTRIBUTE_MUST_ENTER"> 
    <locale language="fr">Le '%1s' doit être saisi si le '%2s' est saisi.</locale> 
  </message>  
  <message name="ERR_ATTRIBUTE_MUST_NOT_ENTER"> 
    <locale language="fr">Le '%1s' ne doit pas être saisi si le '%2s' est saisi.</locale> 
  </message>  
  <message name="ERR_ATLEAST_ONE_ATTRIBUTE_MUST_ENTER"> 
    <locale language="fr">Au moins un '%1s' et '%2s' doivent être saisis.</locale> 
  </message>  
  <message name="ERR_ENTER_ONLY_ONE_ATTRIBUTE"> 
    <locale language="fr">'%1s' ou '%2s' doit être saisi, mais pas les deux.</locale> 
  </message>  
  <message name="ERR_CURRENT_DATE_OPTIONS_NOT_SPECIFIED"> 
    <locale language="fr">Les options de date doivent être spécifiées.</locale> 
  </message>  
  <!-- End,DependentValidator -->  
  <!--  START OF COMPARISON VALIDATOR -->  
  <message name="ERR_COMPARE_GREATERTHAN"> 
    <locale language="fr">'%1s' doit être supérieur à '%2s'.</locale> 
  </message>  
  <message name="ERR_COMPARE_LESSTHAN"> 
    <locale language="fr">'%1s' doit être inférieur à '%2s'.</locale> 
  </message>  
  <message name="ERR_COMPARE_LESSTHAN_EQUALTO"> 
    <locale language="fr">'%1s' doit être inférieur ou égal à '%2s'.</locale> 
  </message>  
  <message name="ERR_COMPARE_GREATERTHAN_EQUALTO"> 
    <locale language="fr">'%1s' doit être supérieur ou égal à '%2s'.</locale> 
  </message>  
  <message name="ERR_COMPARE_IS_EQUALTO"> 
    <locale language="fr">'%1s' doit être égal à '%2s'.</locale> 
  </message>  
  <message name="ERR_COMPARE_NOT_EQUALTO"> 
    <locale language="fr">%1s ne doit pas être égal à %2s.</locale> 
  </message>  
  <message name="ERR_UNKNOWN_COMPARATOR"> 
    <locale language="fr">Comparateur inconnu détecté.</locale> 
  </message>  
  <message name="ERR_COMPARE_DATE_GREATERTHAN"> 
    <locale language="fr">'%1s' doit être postérieure à '%2s'.</locale> 
  </message>  
  <message name="ERR_COMPARE_DATE_LESSTHAN"> 
    <locale language="fr">'%1s' doit être antérieure à '%2s'.</locale> 
  </message>  
  <message name="ERR_COMPARE_DATE_LESSTHAN_EQUALTO"> 
    <locale language="fr">'%1s' doit coïncider avec ou être antérieure à '%2s'.</locale> 
  </message>  
  <message name="ERR_COMPARE_DATE_GREATERTHAN_EQUALTO"> 
    <locale language="fr">'%1s' doit coïncider avec ou être postérieure à '%2s'.</locale> 
  </message>  
  <message name="ERR_RECEIEVED_DATE"> 
    <locale language="fr">Date de réception</locale> 
  </message>  
  <message name="ERR_EFFECTIVE_DATE"> 
    <locale language="fr">Date d'effet</locale> 
  </message>  
  <!-- END OF MESSAGE FOR COMPARISON VALIDATOR -->  
  <message name="ERR_UNKNOWN_ATTRIBUTE_TYPE"> 
    <locale language="fr">Type d'attribut inconnu détecté.</locale> 
  </message>  
  <message name="ERR_DUPLICATE_EVIDENCETYPE_DATE_RANGE_EXISTS"> 
    <locale language="fr">Un enregistrement %1s existe déjà pour la même période.</locale> 
  </message>  
  <message name="ERR_DUPLICATE_EVIDENCETYPE_ATTRIBUTE_EXISTS"> 
    <locale language="fr">Un enregistrement '%1s' existe déjà pour l'attribut '%2s'.</locale> 
  </message>  
  <message name="ERR_CUSTOM_VALIDATION_MESSAGE"> 
    <locale language="fr">%1s</locale> 
  </message>  
  <message name="ERR_DUPLICATE_VALIDATION_DATE_RANGE_EXISTS"> 
    <locale language="fr">L'enregistrement '%1s' existe déjà pour la période '%2s' - '%3s'.</locale> 
  </message>  
  <!-- Start,DependentValidator for Literal Support -->  
  <message name="ERR_LITERAL_ATTRIBUTE_MUST_ENTER"> 
    <locale language="fr">'%1s' doit être saisi lorsque '%2s' est '%3s'.</locale> 
  </message>  
  <message name="ERR_LITERAL_ATTRIBUTE_MUST_NOT_ENTER"> 
    <locale language="fr">'%1s' ne doit pas être saisi lorsque '%2s' est '%3s'.</locale> 
  </message>  
  <message name="ERR_LITERAL_ATLEAST_ONE_ATTRIBUTE_MUST_ENTER"> 
    <locale language="fr">Au moins un élément de '%1s' comme '%2s' ou '%3s' doit être saisi.</locale> 
  </message>  
  <message name="ERR_LITERAL_ENTER_ONLY_ONE_ATTRIBUTE"> 
    <locale language="fr">'%1s' comme '%2s' ou '%3s' doit être saisi, mais pas les deux.</locale> 
  </message>  
  <!--Bidirectional-->  
  <message name="ERR_ATTRIBUTE_BIDIRECTIOAL_MUST_ENTER"> 
    <locale language="fr">'%2s' doit être saisi lorsque '%1s' est saisi. De même, '%1s' doit être saisi lorsque '%2s' est saisi.</locale> 
  </message>  
  <message name="ERR_ATTRIBUTE_MUST_BIDIRECTIOAL_NOT_ENTER"> 
    <locale language="fr">'%2s' ne doit pas être saisi(e) lorsque '%1s' est saisi(e). De même, '%1s' ne doit pas être saisi(e) lorsque '%2s' est saisi(e).</locale> 
  </message>  
  <message name="ERR_LITERAL_ATTRIBUTE_BIDIRECTIOAL_MUST_ENTER"> 
    <locale language="fr">'%2s' doit être saisi(e) lorsque '%1s' est '%3s'. De même, '%1s' doit être '%3s' lorsque '%2s' est saisi(e).</locale> 
  </message>  
  <message name="ERR_LITERAL_ATTRIBUTE_MUST_BIDIRECTIOAL_NOT_ENTER"> 
    <locale language="fr">'%2s' ne doit pas être saisi(e) lorsque '%1s' est '%3s'. De même, '%1s' ne doit pas être '%3s' lorsque '%2s' est saisi(e).</locale> 
  </message>  
  <!-- End,Bidirectional -->  
  <!-- DEPENDENCY DATE SUPPORT-->  
  <message name="ERR_LITERAL_DATE_ATTRIBUTE_MUST_ENTER"> 
    <locale language="fr">'%1s' doit être saisi(e) lorsque '%2s' est '%3d'.</locale> 
  </message>  
  <message name="ERR_LITERAL_DATE_ATTRIBUTE_MUST_NOT_ENTER"> 
    <locale language="fr">'%1s' ne doit pas être saisi(e) lorsque '%2s' est '%3d'.</locale> 
  </message>  
  <message name="ERR_LITERAL_DATE_ATLEAST_ONE_ATTRIBUTE_MUST_ENTER"> 
    <locale language="fr">Au moins un élément de '%1s' comme '%2s' ou '%3d' doit être saisi.</locale> 
  </message>  
  <message name="ERR_LITERAL_DATE_ENTER_ONLY_ONE_ATTRIBUTE"> 
    <locale language="fr">'%1s' comme '%2d' ou '%3s' doit être saisi(e), mais pas les deux.</locale> 
  </message>  
  <message name="ERR_LITERAL_DATE_ATTRIBUTE_BIDIRECTIOAL_MUST_ENTER"> 
    <locale language="fr">'%2s' doit être saisi(e) lorsque '%1s' est '%3d'. De même, '%1s' doit être saisi(e) comme '%3d' lorsque '%2s' est saisi(e).</locale> 
  </message>  
  <message name="ERR_LITERAL_DATE_ATTRIBUTE_MUST_BIDIRECTIOAL_NOT_ENTER"> 
    <locale language="fr">'%2s' ne doit pas être saisi(e) lorsque '%1s' est '%3d'. De même, '%1s' ne doit pas être saisi(e) comme '%3d' lorsque '%2s' est saisi(e).</locale> 
  </message>  
  <message name="ERR_LITERAL_DATETIME_ATTRIBUTE_MUST_ENTER"> 
    <locale language="fr">'%1s' doit être saisi(e) lorsque '%2s' est '%3z'.</locale> 
  </message>  
  <message name="ERR_LITERAL_DATETIME_ATTRIBUTE_MUST_NOT_ENTER"> 
    <locale language="fr">'%1s' ne doit pas être saisi(e) lorsque '%2s' est '%3z'.</locale> 
  </message>  
  <message name="ERR_LITERAL_DATETIME_ATLEAST_ONE_ATTRIBUTE_MUST_ENTER"> 
    <locale language="fr">Au moins un élément de '%1s' comme '%2s' ou '%3z' doit être saisi.</locale> 
  </message>  
  <message name="ERR_LITERAL_DATETIME_ENTER_ONLY_ONE_ATTRIBUTE"> 
    <locale language="fr">'%1s' comme '%2d' ou '%3z' doit être saisi(e), mais pas les deux.</locale> 
  </message>  
  <message name="ERR_LITERAL_DATETIME_ATTRIBUTE_BIDIRECTIOAL_MUST_ENTER"> 
    <locale language="fr">'%2s' doit être saisi(e) lorsque '%1s' est saisi(e) comme '%3z'. De même, '%1s' doit être saisi(e) comme '%3z' lorsque '%2s' est saisi(e).</locale> 
  </message>  
  <message name="ERR_LITERAL_DATETIME_ATTRIBUTE_MUST_BIDIRECTIOAL_NOT_ENTER"> 
    <locale language="fr">'%2s' ne doit pas être saisi(e) lorsque '%1s' est saisi(e) comme '%3z'. De même, '%1s' ne doit pas être saisi(e) comme '%3z' lorsque '%2s' est saisi(e).</locale> 
  </message>  
  <message name="ERR_UNKNOWN_DEPENDENCY_FOUND"> 
    <locale language="fr">Dépendance inconnue trouvée.</locale> 
  </message>  
  <!-- END OF DEPENDENCY DATE SUPPORT-->  
  <message name="ERR_COMPARE_LITERAL_DATE_GREATERTHAN"> 
    <locale language="fr">'%1s' doit être postérieur(e) à '%2d'.</locale> 
  </message>  
  <message name="ERR_COMPARE_LITERAL_DATE_LESSTHAN"> 
    <locale language="fr">'%1s' doit être antérieur(e) à '%2d'.</locale> 
  </message>  
  <message name="ERR_COMPARE_LITERAL_DATE_NOT_EQUALTO"> 
    <locale language="fr">'%1s' ne doit pas être égal(e) à '%2d'.</locale> 
  </message>  
  <message name="ERR_COMPARE_LITERAL_DATE_EQUALTO"> 
    <locale language="fr">'%1s' doit être égal(e) à '%2d'.</locale> 
  </message>  
  <message name="ERR_COMPARE_LITERAL_DATE_GREATERTHAN_EQUALTO"> 
    <locale language="fr">'%1s' doit coïncider avec ou être postérieur(e) à '%2d'.</locale> 
  </message>  
  <message name="ERR_COMPARE_LITERAL_DATE_LESSTHAN_EQUALTO"> 
    <locale language="fr">'%1s' doit coïncider avec ou être antérieur(e) à '%2d'.</locale> 
  </message>  
  <message name="ERR_COMPARE_LITERAL_DATETIME_GREATERTHAN"> 
    <locale language="fr">'%1s' doit être postérieur(e) à '%2z'.</locale> 
  </message>  
  <message name="ERR_COMPARE_LITERAL_DATETIME_LESSTHAN"> 
    <locale language="fr">'%1s' doit être antérieur(e) à '%2z'.</locale> 
  </message>  
  <message name="ERR_COMPARE_LITERAL_DATETIME_NOT_EQUALTO"> 
    <locale language="fr">'%1s' ne doit pas être égale(e) à '%2z'.</locale> 
  </message>  
  <message name="ERR_COMPARE_LITERAL_DATETIME_EQUALTO"> 
    <locale language="fr">'%1s' doit être égal(e) à '%2z'.</locale> 
  </message>  
  <message name="ERR_COMPARE_LITERAL_DATETIME_GREATERTHAN_EQUALTO"> 
    <locale language="fr">'%1s' doit coïncider avec ou être postérieur(e) à '%2z'.</locale> 
  </message>  
  <message name="ERR_COMPARE_LITERAL_DATETIME_LESSTHAN_EQUALTO"> 
    <locale language="fr">'%1s' doit coïncider avec ou être antérieur(e) à '%2z'.</locale> 
  </message>  
  <message name="ERR_DUPLICATE_DATE_RANGE_DATE_OVERLAP_DATE"> 
    <locale language="fr">L'enregistrement '%1s' existe déjà pour la période '%2d' - '%3d'.</locale> 
  </message>  
  <message name="ERR_SPECIAL_RECEIEVED_DATE"> 
    <locale language="fr">Date de réception</locale> 
  </message>  
  <message name="ERR_SPECIAL_EFFECTIVE_DATE_OF_CHANGE"> 
    <locale language="fr">Date d'effet du changement</locale> 
  </message>  
  <message name="ERR_DEPENDENCY_MUST_ENTER"> 
    <locale language="fr">Si '%1s' est saisi(e), '%2s' doit également être saisi(e).</locale> 
  </message>  
  <message name="ERR_DEPENDENCY_BIDIRECTIONAL_MUST_ENTER"> 
    <locale language="fr">Si '%1s' est saisi(e), '%2s' doit également être saisi(e). De même, si '%2s' est saisi(e), '%1s' doit également être saisi(e).</locale> 
  </message>  
  <message name="ERR_DEPENDENCY_MUST_NOT_ENTER"> 
    <locale language="fr">Si '%1s' est saisi(e), '%2s' ne doit pas être saisi(e).</locale> 
  </message>  
  <message name="ERR_DEPENDENCY_BIDIRECTIONAL_MUST_NOT_ENTER"> 
    <locale language="fr">Si '%1s' est saisi(e), '%2s' ne doit pas être saisi(e). De même, si '%2s' est saisi(e), '%1s' ne doit pas être saisi(e).</locale> 
  </message>  
  <message name="ERR_DEPENDENCY_ATLEAST_ONE"> 
    <locale language="fr">Au moins un '%1s' et '%3s' doivent être saisis.</locale> 
  </message>  
  <message name="ERR_DEPENDENCY_ONLY_ONE"> 
    <locale language="fr">Soit '%1s' doit être saisi(e), soit '%2s' doit être saisi(e).</locale> 
  </message>  
  <message name="ERR_DEPENDENCY_BOTH_LITERAL_MUST_ENTER"> 
    <locale language="fr">Si '%1s' est saisi(e) comme '%2s', alors '%3s' doit également être saisi(e) comme '%4s'.</locale> 
  </message>  
  <message name="ERR_DEPENDENCY_BOTH_DATE_LITERAL_MUST_ENTER"> 
    <locale language="fr">Si '%1s' est saisi(e) comme '%2d', alors '%3s' doit également être saisi(e) comme '%4d'.</locale> 
  </message>  
  <message name="ERR_DEPENDENCY_BOTH_DATE_TIME_LITERAL_MUST_ENTER"> 
    <locale language="fr">Si '%1s' est saisi(e) comme '%2z', alors '%3s' doit également être saisi(e) comme '%4z'.</locale> 
  </message>  
  <message name="ERR_DEPENDENCY_BOTH_STRING_DATE_LITERAL_MUST_ENTER"> 
    <locale language="fr">Si '%1s' est saisi(e) comme '%2s', alors '%3s' doit également être saisi(e) comme '%4d'.</locale> 
  </message>  
  <message name="ERR_DEPENDENCY_BOTH_STRING_DATE_TIME_LITERAL_MUST_ENTER"> 
    <locale language="fr">Si '%1s' est saisi(e) comme '%2s', alors '%3s' doit également être saisi(e) comme '%4z'.</locale> 
  </message>  
  <message name="ERR_DEPENDENCY_BOTH_DATE_STRING_LITERAL_MUST_ENTER"> 
    <locale language="fr">Si '%1s' est saisi(e) comme '%2d', alors '%3s' doit également être saisi(e) comme '%4s'.</locale> 
  </message>  
  <message name="ERR_DEPENDENCY_BOTH_DATE_TIME_STRING_LITERAL_MUST_ENTER"> 
    <locale language="fr">Si '%1s' est saisi(e) comme '%2z', alors '%3s' doit également être saisi(e) comme '%4s'.</locale> 
  </message>  
  <message name="ERR_DEPENDENCY_SOURCE_LITERAL_MUST_ENTER"> 
    <locale language="fr">Si '%1s' est saisi(e) comme '%2s', '%3s' doit également être saisi(e).</locale> 
  </message>  
  <message name="ERR_DEPENDENCY_SOURCE_DATE_LITERAL_MUST_ENTER"> 
    <locale language="fr">Si '%1s' est saisi(e) comme '%2d', '%3s' doit également être saisi(e).</locale> 
  </message>  
  <message name="ERR_DEPENDENCY_SOURCE_DATE_TIME_LITERAL_MUST_ENTER"> 
    <locale language="fr">Si '%1s' est saisi(e) comme '%2z', '%3s' doit également être saisi(e).</locale> 
  </message>  
  <message name="ERR_DEPENDENCY_TARGET_LITERAL_MUST_ENTER"> 
    <locale language="fr">Si '%1s' est saisi(e), alors '%2s'doit également être saisi(e) comme '%3s'.</locale> 
  </message>  
  <message name="ERR_DEPENDENCY_TARGET_DATE_LITERAL_MUST_ENTER"> 
    <locale language="fr">Si '%1s' est saisi(e), alors '%2s'doit également être saisi(e) comme '%3d'.</locale> 
  </message>  
  <message name="ERR_DEPENDENCY_TARGET_DATE_TIME_LITERAL_MUST_ENTER"> 
    <locale language="fr">Si '%1s' est saisi(e), alors '%2s'doit également être saisi(e) comme '%3z'.</locale> 
  </message>  
  <message name="ERR_DEPENDENCY_TARGET_LITERAL_MUST_ENTER_SOURCE"> 
    <locale language="fr">Si '%1s' est saisi(e) comme '%2s', '%3s' doit également être saisi(e).</locale> 
  </message>  
  <message name="ERR_DEPENDENCY_TARGET_DATE_LITERAL_MUST_ENTER_SOURCE"> 
    <locale language="fr">Si '%1s' est saisi(e) comme '%2d', '%3s' doit également être saisi(e).</locale> 
  </message>  
  <message name="ERR_DEPENDENCY_TARGET_DATE_TIME_LITERAL_MUST_ENTER_SOURCE"> 
    <locale language="fr">Si '%1s' est saisi(e) comme '%2z', '%3s' doit également être saisi(e).</locale> 
  </message>  
  <message name="ERR_DEPENDENCY_BIDIRECTIONAL_BOTH_LITERAL_MUST_ENTER"> 
    <locale language="fr">Si '%1s' est saisi(e) comme '%2s', alors '%3s' doit également être saisi(e) comme '%4s'. De même, si '%3s' est saisi(e) comme '%4s' , alors '%1s' doit également être saisi(e) comme '%2s'.</locale> 
  </message>  
  <message name="ERR_DEPENDENCY_BIDIRECTIONAL_BOTH_DATE_LITERAL_MUST_ENTER"> 
    <locale language="fr">Si '%1s' est saisi(e) comme '%2d', alors '%3s' doit également être saisi(e) comme '%4d'. De même, si '%3s' est saisi(e) comme '%4d' , alors '%1s' doit également être saisi(e) comme '%2d'.</locale> 
  </message>  
  <message name="ERR_DEPENDENCY_BIDIRECTIONAL_BOTH_DATE_TIME_LITERAL_MUST_ENTER"> 
    <locale language="fr">Si '%1s' est saisi(e) comme '%2z', alors '%3s' doit également être saisi(e) comme '%4z'. De même, si '%3s' est saisi(e) comme '%4z' , alors '%1s' doit également être saisi(e) comme '%2z'.</locale> 
  </message>  
  <!--BOTH MUST LITERALS-NEW-->  
  <message name="ERR_DEPENDENCY_BIDIRECTIONAL_BOTH_STRING_DATE_LITERAL_MUST_ENTER"> 
    <locale language="fr">Si '%1s' est saisi(e) comme '%2s', alors '%3s' doit également être saisi(e) comme '%4d'. De même, si '%3s' est saisi(e) comme '%4d' , alors '%1s' doit également être saisi(e) comme '%2s'.</locale> 
  </message>  
  <message name="ERR_DEPENDENCY_BIDIRECTIONAL_BOTH_STRING_DATE_TIME_LITERAL_MUST_ENTER"> 
    <locale language="fr">Si '%1s' est saisi(e) comme '%2s', alors '%3s' doit également être saisi(e) comme '%4z'. De même, si '%3s' est saisi(e) comme '%4z' , alors '%1s' doit également être saisi(e) comme '%2s'.</locale> 
  </message>  
  <message name="ERR_DEPENDENCY_BIDIRECTIONAL_BOTH_DATE_STRING_LITERAL_MUST_ENTER"> 
    <locale language="fr">Si '%1s' est saisi(e) comme '%2d', alors '%3s' doit également être saisi(e) comme '%4s'. De même, si '%3s' est saisi(e) comme '%4d' , alors '%1s' doit également être saisi(e) comme '%2d'.</locale> 
  </message>  
  <message name="ERR_DEPENDENCY_BIDIRECTIONAL_BOTH_DATE_TIME_STRING_LITERAL_MUST_ENTER"> 
    <locale language="fr">Si '%1s' est saisi(e) comme '%2z', alors '%3s' doit également être saisi(e) comme '%4s'. De même, si '%3s' est saisi(e) comme '%4z' , alors '%1s' doit également être saisi(e) comme '%2z'.</locale> 
  </message>  
  <!--BOTH MUST LITERALS-NEW-->  
  <message name="ERR_DEPENDENCY_BIDIRECTIONAL_SOURCE_LITERAL_MUST_ENTER"> 
    <locale language="fr">Si '%1s' est saisi(e) comme '%2s', alors '%3s' doit également être saisi(e). De même, si '%3s' est saisi(e), alors '%1s' doit également être saisi(e) comme '%2s'.</locale> 
  </message>  
  <message name="ERR_DEPENDENCY_BIDIRECTIONAL_SOURCE_DATE_LITERAL_MUST_ENTER"> 
    <locale language="fr">Si '%1s' est saisi(e) comme '%2d', alors '%3s' doit également être saisi(e). De même, si '%3s' est saisi(e), alors '%1s' doit également être saisi(e) comme '%2d'.</locale> 
  </message>  
  <message name="ERR_DEPENDENCY_BIDIRECTIONAL_SOURCE_DATE_TIME_LITERAL_MUST_ENTER"> 
    <locale language="fr">Si '%1s' est saisi(e) comme '%2z', alors '%3s' doit également être saisi(e). De même, si '%3s' est saisi(e), alors '%1s' doit également être saisi(e) comme '%2z'.</locale> 
  </message>  
  <message name="ERR_DEPENDENCY_BIDIRECTIONAL_TARGET_LITERAL_MUST_ENTER"> 
    <locale language="fr">Si '%1s' est saisi(e), alors '%2s' doit également être saisi(e) comme '%3s'. De même, si '%2s' est saisi(e) comme '%3s', alors '%1s' doit être saisi(e).</locale> 
  </message>  
  <message name="ERR_DEPENDENCY_BIDIRECTIONAL_TARGET_DATE_LITERAL_MUST_ENTER"> 
    <locale language="fr">Si '%1s' est saisi(e), alors '%2s' doit également être saisi(e) comme '%3d'. De même, si '%2s' est saisi(e) comme '%3d', alors '%1s' doit être saisi(e).</locale> 
  </message>  
  <message name="ERR_DEPENDENCY_BIDIRECTIONAL_TARGET_DATE_TIME_LITERAL_MUST_ENTER"> 
    <locale language="fr">Si '%1s' est saisi(e), alors '%2s' doit également être saisi(e) comme '%3z'. De même, si '%2s' est saisi(e) comme '%3z', alors '%1s' doit être saisi(e).</locale> 
  </message>  
  <message name="ERR_DEPENDENCY_BIDIRECTIONAL_TARGET_LITERAL_MUST_ENTER_SOURCE"> 
    <locale language="fr">Si '%1s' est saisi(e) comme '%2s', alors '%3s' doit également être saisi(e). De même, si '%3s' est saisi(e), alors '%1s' doit également être saisi(e) comme '%2s'.</locale> 
  </message>  
  <message name="ERR_DEPENDENCY_BIDIRECTIONAL_TARGET_DATE_LITERAL_MUST_ENTER_SOURCE"> 
    <locale language="fr">Si '%1s' est saisi(e) comme '%2d', alors '%3s' doit également être saisi(e). De même, si '%3s' est saisi(e), alors '%1s' doit également être saisi(e) comme '%2d'.</locale> 
  </message>  
  <message name="ERR_DEPENDENCY_BIDIRECTIONAL_TARGET_DATE_TIME_LITERAL_MUST_ENTER_SOURCE"> 
    <locale language="fr">Si '%1s' est saisi(e) comme '%2z', alors '%3s' doit également être saisi(e). De même, si '%3s' est saisi(e), alors '%1s' doit également être saisi(e) comme '%2z'.</locale> 
  </message>  
  <message name="ERR_DEPENDENCY_LITERAL_MUST_NOT_ENTER"> 
    <locale language="fr">Si '%1s' est saisi(e) comme '%2s', alors '%3s' ne doit pas être saisi(e) comme '%4s'.</locale> 
  </message>  
  <message name="ERR_DEPENDENCY_DATE_LITERAL_MUST_NOT_ENTER"> 
    <locale language="fr">Si '%1s' est saisi(e) comme '%2d', alors '%3s' ne doit pas être saisi(e) comme '%4d'.</locale> 
  </message>  
  <message name="ERR_DEPENDENCY_DATE_TIME_LITERAL_MUST_NOT_ENTER"> 
    <locale language="fr">Si '%1s' est saisi(e) comme '%2z', alors '%3s' ne doit pas être saisi(e) comme '%4z'.</locale> 
  </message>  
  <!-- MUST NOT ENTER NEW-->  
  <message name="ERR_DEPENDENCY_STRING_DATE_LITERAL_MUST_NOT_ENTER"> 
    <locale language="fr">Si '%1s' est saisi(e) comme '%2s', alors '%3s' ne doit pas être saisi(e) comme '%4d'.</locale> 
  </message>  
  <message name="ERR_DEPENDENCY_STRING_DATE_TIME_LITERAL_MUST_NOT_ENTER"> 
    <locale language="fr">Si '%1s' est saisi(e) comme '%2s', alors '%3s' ne doit pas être saisi(e) comme '%4z'.</locale> 
  </message>  
  <message name="ERR_DEPENDENCY_DATE_STRING_LITERAL_MUST_NOT_ENTER"> 
    <locale language="fr">Si '%1s' est saisi(e) comme '%2d', alors '%3s' ne doit pas être saisi(e) comme '%4s'.</locale> 
  </message>  
  <message name="ERR_DEPENDENCY_DATE_TIME_STRING_LITERAL_MUST_NOT_ENTER"> 
    <locale language="fr">Si '%1s' est saisi(e) comme '%2d', alors '%3s' ne doit pas être saisi(e) comme '%4s'.</locale> 
  </message>  
  <!-- MUST NOT ENTER NEW-->  
  <message name="ERR_DEPENDENCY_SOURCE_LITERAL_MUST_NOT_ENTER"> 
    <locale language="fr">Si '%1s' est saisi comme '%2s', '%3s' ne doit pas être saisi.</locale> 
  </message>  
  <message name="ERR_DEPENDENCY_SOURCE_DATE_LITERAL_MUST_NOT_ENTER"> 
    <locale language="fr">Si '%1s' est saisi comme '%2d', '%3s' ne doit pas être saisi.</locale> 
  </message>  
  <message name="ERR_DEPENDENCY_SOURCE_DATE_TIME_LITERAL_MUST_NOT_ENTER"> 
    <locale language="fr">Si '%1s' est saisi comme '%2z', '%3s' ne doit pas être saisi.</locale> 
  </message>  
  <message name="ERR_DEPENDENCY_TARGET_LITERAL_MUST_NOT_ENTER"> 
    <locale language="fr">Si '%1s' est saisi(e), alors '%2s' ne doit pas être saisi(e) comme '%3s'.</locale> 
  </message>  
  <message name="ERR_DEPENDENCY_TARGET_DATE_LITERAL_MUST_NOT_ENTER"> 
    <locale language="fr">Si '%1s' est saisi(e), alors '%2s' ne doit pas être saisi(e) comme '%3d'.</locale> 
  </message>  
  <message name="ERR_DEPENDENCY_TARGET_DATE_TIME_LITERAL_MUST_NOT_ENTER"> 
    <locale language="fr">Si '%1s' est saisi(e), alors '%2s' ne doit pas être saisi(e) comme '%3z'.</locale> 
  </message>  
  <message name="ERR_DEPENDENCY_BIDIRECTIONAL_BOTH_LITERAL_MUST_NOT_ENTER"> 
    <locale language="fr">Si '%1s' est saisi(e) comme '%2s', alors '%3s' ne doit pas être saisi(e) comme '%4s'. De même, si '%3s' est saisi(e) comme '%4s', alors '%1s' ne doit pas être saisi(e) comme '%2s'.</locale> 
  </message>  
  <message name="ERR_DEPENDENCY_BIDIRECTIONAL_BOTH_DATE_LITERAL_MUST_NOT_ENTER"> 
    <locale language="fr">Si '%1s' est saisi(e) comme '%2d', alors '%3s' ne doit pas être saisi(e) comme '%4d'. De même, si '%3s' est saisi(e) comme '%4d', alors '%1s' ne doit pas être saisi(e) comme '%2d'.</locale> 
  </message>  
  <message name="ERR_DEPENDENCY_BIDIRECTIONAL_BOTH_DATE_TIME_LITERAL_MUST_NOT_ENTER"> 
    <locale language="fr">Si '%1s' est saisi(e) comme '%2z', alors '%3s' ne doit pas être saisi(e) comme '%4z'. De même, si '%3s' est saisi(e) comme '%4z', alors '%1s' ne doit pas être saisi(e) comme '%2z'.</locale> 
  </message>  
  <!-- Must Not Enter New -->  
  <message name="ERR_DEPENDENCY_BIDIRECTIONAL_BOTH_STRING_DATE_LITERAL_MUST_NOT_ENTER"> 
    <locale language="fr">Si '%1s' est saisi(e) comme '%2s', alors '%3s' ne doit pas être saisi(e) comme '%4d'. De même, si '%3s' est saisi(e) comme '%4d', alors '%1s' ne doit pas être saisi(e) comme '%2s'.</locale> 
  </message>  
  <message name="ERR_DEPENDENCY_BIDIRECTIONAL_BOTH_STRING_DATE_TIME_LITERAL_MUST_NOT_ENTER"> 
    <locale language="fr">Si '%1s' est saisi(e) comme '%2s', alors '%3s' ne doit pas être saisi(e) comme '%4z'. De même, si '%3s' est saisi(e) comme '%4z', alors '%1s' ne doit pas être saisi(e) comme '%2s'.</locale> 
  </message>  
  <message name="ERR_DEPENDENCY_BIDIRECTIONAL_BOTH_DATE_STRING_LITERAL_MUST_NOT_ENTER"> 
    <locale language="fr">Si '%1s' est saisi(e) comme '%2d', alors '%3s' ne doit pas être saisi(e) comme '%4s'. De même, si '%3s' est saisi(e) comme '%4s', alors '%1s' ne doit pas être saisi(e) comme '%2d'.</locale> 
  </message>  
  <message name="ERR_DEPENDENCY_BIDIRECTIONAL_BOTH_DATE_TIME_STRING_LITERAL_MUST_NOT_ENTER"> 
    <locale language="fr">Si '%1s' est saisi(e) comme '%2z', alors '%3s' ne doit pas être saisi(e) comme '%4s'. De même, si '%3s' est saisi(e) comme '%4s', alors '%1s' ne doit pas être saisi(e) comme '%2z'.</locale> 
  </message>  
  <!-- Must Not Enter New -->  
  <message name="ERR_DEPENDENCY_BIDIRECTIONAL_SOURCE_LITERAL_MUST_NOT_ENTER"> 
    <locale language="fr">Si '%1s' est saisi comme '%2s', '%3s' ne doit pas être saisi. De même, si '%3s' est saisi, '%1s' ne doit pas être saisi comme '%2s'.</locale> 
  </message>  
  <message name="ERR_DEPENDENCY_BIDIRECTIONAL_SOURCE_DATE_LITERAL_MUST_NOT_ENTER"> 
    <locale language="fr">Si '%1s' est saisi comme '%2d', '%3s' ne doit pas être saisi. De même, si '%3s' est saisi, '%1s' ne doit pas être saisi comme '%2d'.</locale> 
  </message>  
  <message name="ERR_DEPENDENCY_BIDIRECTIONAL_SOURCE_DATE_TIME_LITERAL_MUST_NOT_ENTER"> 
    <locale language="fr">Si '%1s' est saisi comme '%2z', '%3s' ne doit pas être saisi. De même, si '%3s' est saisi, '%1s' ne doit pas être saisi comme '%2z'.</locale> 
  </message>  
  <message name="ERR_DEPENDENCY_BIDIRECTIONAL_TARGET_LITERAL_MUST_NOT_ENTER"> 
    <locale language="fr">Si '%1s' est saisi(e), alors '%2s' ne doit pas être saisi(e) comme '%3s'. De même, si '%2s' est saisi(e) comme '%3s', alors '%1s' ne doit pas être saisi(e).</locale> 
  </message>  
  <message name="ERR_DEPENDENCY_BIDIRECTIONAL_TARGET_DATE_LITERAL_MUST_NOT_ENTER"> 
    <locale language="fr">Si '%1s' est saisi(e), alors '%2s' ne doit pas être saisi(e) comme '%3d'. De même, si '%2s' est saisi(e) comme '%3d', alors '%1s' ne doit pas être saisi(e).</locale> 
  </message>  
  <message name="ERR_DEPENDENCY_BIDIRECTIONAL_TARGET_DATE_TIME_LITERAL_MUST_NOT_ENTER"> 
    <locale language="fr">Si '%1s' est saisi(e), alors '%2s' ne doit pas être saisi(e) comme '%3z'. De même, si '%2s' est saisi(e) comme '%3z', alors '%1s' ne doit pas être saisi(e).</locale> 
  </message>  
  <message name="ERR_DEPENDENCY_LITERAL_BOTH_ATLEAST_ONE"> 
    <locale language="fr">Au moins un(e) '%1s' doit être saisi(e) comme '%2s' et '%3s' doit être saisi(e) comme '%4s'.</locale> 
  </message>  
  <message name="ERR_DEPENDENCY_LITERAL_BOTH_DATE_ATLEAST_ONE"> 
    <locale language="fr">Au moins un(e) '%1s' doit être saisi(e) comme '%2d' et '%3s' doit être saisi(e) comme '%4d'.</locale> 
  </message>  
  <message name="ERR_DEPENDENCY_LITERAL_BOTH_DATE_TIME_ATLEAST_ONE"> 
    <locale language="fr">Au moins un(e) '%1s' doit être saisi(e) comme '%2z' et '%3s' doit être saisi(e) comme '%4z'.</locale> 
  </message>  
  <!--NEW ATLEAST ONE-->  
  <message name="ERR_DEPENDENCY_LITERAL_BOTH_STRING_DATE_ATLEAST_ONE"> 
    <locale language="fr">Au moins un(e) '%1s' doit être saisi(e) comme '%2s' et '%3s' doit être saisi(e) comme '%4d'.</locale> 
  </message>  
  <message name="ERR_DEPENDENCY_LITERAL_BOTH_STRING_DATE_TIME_ATLEAST_ONE"> 
    <locale language="fr">Au moins un(e) '%1s' doit être saisi(e) comme '%2s' et '%3s' doit être saisi(e) comme '%4z'.</locale> 
  </message>  
  <message name="ERR_DEPENDENCY_LITERAL_BOTH_DATE_STRING_ATLEAST_ONE"> 
    <locale language="fr">Au moins un(e) '%1d' doit être saisi(e) comme '%2s' et '%3s' doit être saisi(e) comme '%4s'.</locale> 
  </message>  
  <message name="ERR_DEPENDENCY_LITERAL_BOTH_DATE_TIME_STRING_ATLEAST_ONE"> 
    <locale language="fr">Au moins un(e) '%1z' doit être saisi(e) comme '%2s' et '%3s' doit être saisi(e) comme '%4s'.</locale> 
  </message>  
  <!-- NEW ATLEAST ONE-->  
  <message name="ERR_DEPENDENCY_SOURCE_LITERAL_ATLEAST_ONE"> 
    <locale language="fr">Au moins un '%1s' comme '%2s' et '%3s' doivent être saisis.</locale> 
  </message>  
  <message name="ERR_DEPENDENCY_SOURCE_DATE_LITERAL_ATLEAST_ONE"> 
    <locale language="fr">Au moins un '%1s' comme '%2d' et '%3s' doivent être saisis.</locale> 
  </message>  
  <message name="ERR_DEPENDENCY_SOURCE_DATE_TIME_LITERAL_ATLEAST_ONE"> 
    <locale language="fr">Au moins un '%1s' comme '%2z' et '%3s' doivent être saisis.</locale> 
  </message>  
  <message name="ERR_DEPENDENCY_TARGET_LITERAL_ATLEAST_ONE"> 
    <locale language="fr">Au moins un(e) '%1s' et '%2s' comme '%3s' doivent être saisi(e)s.</locale> 
  </message>  
  <message name="ERR_DEPENDENCY_TARGET_DATE_LITERAL_ATLEAST_ONE"> 
    <locale language="fr">Au moins un(e) '%1s' et '%2s' comme '%3d' doivent être saisi(e)s.</locale> 
  </message>  
  <message name="ERR_DEPENDENCY_TARGET_DATE_TIME_LITERAL_ATLEAST_ONE"> 
    <locale language="fr">Au moins un(e) '%1s' et '%2s' comme '%3z' doivent être saisi(e)s.</locale> 
  </message>  
  <message name="ERR_DEPENDENCY_LITERAL_BOTH_ONLY_ONE"> 
    <locale language="fr">Soit '%1s' doit être saisi(e) comme '%2s', soit '%3s' doit être saisi(e) comme '%4s'.</locale> 
  </message>  
  <message name="ERR_DEPENDENCY_LITERAL_BOTH_DATE_ONLY_ONE"> 
    <locale language="fr">Soit '%1s' doit être saisi(e) comme '%2d', soit '%3s' doit être saisi(e) comme '%4d'.</locale> 
  </message>  
  <message name="ERR_DEPENDENCY_LITERAL_BOTH_DATE_TIME_ONLY_ONE"> 
    <locale language="fr">Soit '%1s' doit être saisi(e) comme '%2z', soit '%3s' doit être saisi(e) comme '%4z'.</locale> 
  </message>  
  <!--NEW ONLY ONE-->  
  <message name="ERR_DEPENDENCY_LITERAL_BOTH_STRING_DATE_ONLY_ONE"> 
    <locale language="fr">Soit '%1s' doit être saisi(e) comme '%2s', soit '%3s' doit être saisi(e) comme '%4d'.</locale> 
  </message>  
  <message name="ERR_DEPENDENCY_LITERAL_BOTH_STRING_DATE_TIME_ONLY_ONE"> 
    <locale language="fr">Soit '%1s' doit être saisi(e) comme '%2s', soit '%3s' doit être saisi(e) comme '%4z'.</locale> 
  </message>  
  <message name="ERR_DEPENDENCY_LITERAL_BOTH_DATE_STRING_ONLY_ONE"> 
    <locale language="fr">Soit '%1s' doit être saisi(e) comme '%2d', soit '%3s' doit être saisi(e) comme '%4s'.</locale> 
  </message>  
  <message name="ERR_DEPENDENCY_LITERAL_BOTH_DATE_TIME_STRING_ONLY_ONE"> 
    <locale language="fr">Soit '%1s' doit être saisi(e) comme '%2z', soit '%3s' doit être saisi(e) comme '%4s'.</locale> 
  </message>  
  <!--NEW ONLY ONE-->  
  <message name="ERR_DEPENDENCY_SOURCE_LITERAL_ONLY_ONE"> 
    <locale language="fr">'%1s' doit être saisi comme '%2s' ou '%3s' doit être saisi, mais pas les deux.</locale> 
  </message>  
  <message name="ERR_DEPENDENCY_SOURCE_DATE_LITERAL_ONLY_ONE"> 
    <locale language="fr">'%1s' doit être saisi comme '%2d' ou '%3s' doit être saisi, mais pas les deux.</locale> 
  </message>  
  <message name="ERR_DEPENDENCY_SOURCE_DATE_TIME_LITERAL_ONLY_ONE"> 
    <locale language="fr">'%1s' doit être saisi comme '%2z' ou '%3s' doit être saisi, mais pas les deux.</locale> 
  </message>  
  <message name="ERR_DEPENDENCY_TARGET_LITERAL_ONLY_ONE"> 
    <locale language="fr">Soit '%1s' doit être saisi(e), soit '%2s' doit être saisi(e) comme '%3s'.</locale> 
  </message>  
  <message name="ERR_DEPENDENCY_TARGET_DATE_LITERAL_ONLY_ONE"> 
    <locale language="fr">Soit '%1s' doit être saisi(e), soit '%2s' doit être saisi(e) comme '%3d'.</locale> 
  </message>  
  <message name="ERR_DEPENDENCY_TARGET_DATE_TIME_LITERAL_ONLY_ONE"> 
    <locale language="fr">Soit '%1s' doit être saisi(e), soit '%2s' doit être saisi(e) comme '%3z'.</locale> 
  </message>  
  <message name="ERR_DEPENDENCY_ATLEAST_ONE_ATTRIBUTE"> 
    <locale language="fr">Au moins un '%1s' et '%2s' doivent être saisis.</locale> 
  </message>  
  <message name="ERR_COMPLEX_VALIDATION_MESSAGE"> 
    <locale language="fr">%1s</locale> 
  </message>  
  <message name="ERR_UNSUPPORTED_COMPARISON_VALIDATION_FOUND"> 
    <locale language="fr">Impossible de valider les attributs des informations collectées. Veuillez contacter votre administrateur système.</locale> 
  </message>  
  <message name="ERR_COMPLEX_VALIDATION_OR_CONJUNCTION"> 
    <!--  START NON-TRANSLATABLE  -->  
    <locale language="fr">OR</locale>  
    <!--  END NON-TRANSLATABLE  --> 
  </message>  
  <message name="ERR_COMPLEX_VALIDATION_AND_CONJUNCTION"> 
    <!--  START NON-TRANSLATABLE  -->  
    <locale language="fr">AND</locale>  
    <!--  END NON-TRANSLATABLE  --> 
  </message>  
  <message name="ERR_VALIDATION_OPERATOR_BEFORE_DATE"> 
    <locale language="fr">doit être inférieur à</locale> 
  </message>  
  <message name="ERR_VALIDATION_OPERATOR_AFTER_DATE"> 
    <locale language="fr">doit être supérieur à</locale> 
  </message>  
  <message name="ERR_VALIDATION_OPERATOR_ON_OR_AFTER_DATE"> 
    <locale language="fr">doit être supérieur ou égal à</locale> 
  </message>  
  <message name="ERR_VALIDATION_OPERATOR_ON_OR_BEFORE_DATE"> 
    <locale language="fr">doit être inférieur ou égal à</locale> 
  </message>  
  <message name="ERR_VALIDATION_OPERATOR_EQUAL_TO"> 
    <locale language="fr">doit être égal à</locale> 
  </message>  
  <message name="ERR_VALIDATION_OPERATOR_NOT_EQUAL_TO"> 
    <locale language="fr">ne doit pas être égal à</locale> 
  </message>  
  <message name="ERR_VALIDATION_OPERATOR_GREATER_THAN"> 
    <locale language="fr">doit être supérieur à</locale> 
  </message>  
  <message name="ERR_VALIDATION_OPERATOR_LESS_THAN"> 
    <locale language="fr">doit être inférieur à</locale> 
  </message>  
  <message name="ERR_VALIDATION_OPERATOR_GREATER_THAN_EQUAL_TO"> 
    <locale language="fr">doit être supérieur ou égal à</locale> 
  </message>  
  <message name="ERR_VALIDATION_OPERATOR_LESS_THAN_EQUAL_TO"> 
    <locale language="fr">doit être inférieur ou égal à</locale> 
  </message>  
  <message name="ERR_DUPLICATE_DATE_ATTRIBUTE_EXISTS"> 
    <locale language="fr">L'enregistrement d'informations collectées pour lequel %1s est saisi(e) comme '%2d' existe déjà.</locale> 
  </message>  
  <message name="ERR_DUPLICATE_DATE_TIME_ATTRIBUTE_EXISTS"> 
    <locale language="fr">L'enregistrement d'informations collectées pour lequel %1s est saisi(e) comme '%2z' existe déjà.</locale> 
  </message>  
  <message name="ERR_DUPLICATE_ATTRIBUTE_EXISTS"> 
    <locale language="fr">L'enregistrement d'informations collectées pour lequel %1s est saisi(e) comme '%2s' existe déjà.</locale> 
  </message>  
  <message name="ERR_DUPLICATE_ATTRIBUTE_DATERANGE_EXISTS"> 
    <locale language="fr">L'enregistrement d'informations collectées avec %1s comme '%2s' existe déjà pour la période '%3d' - '%4d'.</locale> 
  </message>  
  <message name="ERR_INVALID_INTEGER"> 
    <locale language="fr">Impossible de valider les attributs d'informations collectées. Motif - '%1s' n'est pas une valeur d'entier valide.</locale> 
  </message>  
  <message name="ERR_INVALID_BOOLEAN_LITERAL_TRUE"> 
    <locale language="fr">true</locale> 
  </message>  
  <message name="ERR_INVALID_BOOLEAN_LITERAL_FALSE"> 
    <locale language="fr">false</locale> 
  </message> 
</messages>
