<?xml version="1.0" encoding="UTF-8"?>
<!--
  Licensed Materials - Property of IBM
 
  Copyright IBM Corporation 2012. All Rights Reserved.

  US Government Users Restricted Rights - Use, duplication or disclosure 
  restricted by GSA ADP Schedule Contract with IBM Corp.
-->
<!--
Copyright 2009-2011 Curam Software Ltd.
All rights reserved.

This software is the confidential and proprietary information of Curam
Software, Ltd. ("Confidential Information").  You shall not
disclose such Confidential Information and shall use it only in accordance
with the terms of the license agreement you entered into with Curam Software.
-->
<messages package="curam.message">


  <message name="ERR_INTAKE_FV_NO_PERSON_SELECTED">
    <locale language="en">Please select one person from the list to start a new intake.</locale>
  </message>
  <message name="INF_PARENTHESIS_SEPARATOR">
    <locale language="en">%1s (%2s)</locale>
  </message>
  <message name="MSG_AND">
    <locale language="en">and</locale>
  </message>
  <message name="TEXT_ANONYMOUS_CLIENT">
    <locale language="en">Anonymous Client</locale>
  </message>
  <message name="TEXT_URGENT_ALERT">
    <locale language="en">URGENT ALERT</locale>
  </message>
  <!-- BEGIN, CR00261333, SS -->
  <!-- BEGIN,CR00279144 MN -->
  <message name="ERR_INTAKE_FV_MIN_CRITERIA_NOT_ENTERED">
    <locale language="en">User must input at least Reference, First Name and Date of Birth or Last Name.</locale>
  </message>
  <!-- END, CR00279144 MN -->
  <message name="ERR_WRONG_DATE_FORMAT">
    <locale language="en">The field Date of Birth must be a date in the format 'M/d/yyyy'.</locale>
  </message>
  <!-- END, CR00261333 -->
</messages>
