<?xml version="1.0" encoding="UTF-8"?>

<!--
  Licensed Materials - Property of IBM
  
  Copyright IBM Corporation 2012. All Rights Reserved.
 
  US Government Users Restricted Rights - Use, duplication or disclosure 
  restricted by GSA ADP Schedule Contract with IBM Corp.
-->
<!--
Copyright 2010 Curam Software Ltd.
All rights reserved.
This software is the confidential and proprietary information of Curam
Software, Ltd. ("Confidential Information").  You shall not
disclose such Confidential Information and shall use it only in accordance
with the terms of the license agreement you entered into with Curam Software.
-->
<messages package="curam.citizenworkspace.message"> 
  <message name="ERR_CITIZEN_ACCOUNT_WRONG_USER_ATTEMPT"> 
    <locale language="fr">Vous ne disposez pas de privilèges pour accéder à cette page.</locale> 
  </message>  
  <message name="ERR_CASE_OWNER_SHOULD_BE_INTERNAL_USER"> 
    <locale language="fr">Les propriétaires de dossier doivent être des utilisateurs internes.</locale> 
  </message>  
  <message name="ERR_PROVIDER_MODAL_INVOKED_WITHOUT_CPM"> 
    <locale language="fr">La fonctionnalité permettant d'afficher le modal du prestataire de compte citoyen nécessite que le module CPM soit installé.</locale> 
  </message>  
  <message name="ERR_INVALID_CREDIT_DEBIT_VALUE"> 
    <locale language="fr">Une valeur inattendue a été rencontrée dans la table de codes Crédit Débit.</locale> 
  </message> 
</messages>
