<?xml version="1.0" encoding="UTF-8"?>
<!--
  Licensed Materials - Property of IBM
 
  Copyright IBM Corporation 2012. All Rights Reserved.

  US Government Users Restricted Rights - Use, duplication or disclosure 
  restricted by GSA ADP Schedule Contract with IBM Corp.
-->
<!-- 
Copyright 2003-2005, 2007, 2009, 2010 Curam Software Ltd.
All rights reserved.

This software is the confidential and proprietary information of Curam
Software, Ltd. ("Confidential Information").  You shall not
disclose such Confidential Information and shall use it only in accordance
with the terms of the license agreement you entered into with Curam Software.
-->
<messages package="curam.message">
  <message name="INF_BPOCASESEARCH_NO_MATCH">
    <locale language="en">No case could be found which matched the search criteria.</locale>
  </message>
  <message name="INF_BPOCASESEARCH_NO_CASE_REFERENCE_SPECIFIED">
    <locale language="en">You must specify a case reference number.</locale>
  </message>
  <message name="ERR_BPOCASESEARCH_NO_CRITERIA_SPECIFIED">
    <locale language="en">At least one search criteria must be entered.</locale>
  </message>
  <message name="ERR_BPOCASESEARCH_ADDITIONAL_CRITERIA">
    <locale language="en">Please specify additional search criteria.</locale>
  </message>
  <message name="ERR_BPOCASESEARCH_NO_TYPE">
    <locale language="en">Please specify a type.</locale>
  </message>
  <message name="ERR_BPOCASESEARCH_NO_CATEGORY">
    <locale language="en">Please specify a category.</locale>
  </message>
  <message name="ERR_BPOCASESEARCH_MISSING_CRITERIA">
    <locale language="en">Please refine the search criteria. At least one more search criteria must be specified.</locale>
  </message>
  <message name="ERR_CASESEARCH_UNIMPLEMENTED">
    <locale language="en">No Case Search implemented. Please contact an Administrator.</locale>
  </message>
  <message name="ERR_CASESEARCH_MAXIMUM">
    <locale language="en">The maximum search result has been exceeded. Please refine your search.</locale>
  </message>
  <message name="ERR_BPOCASESEARCH_FV_START_DATE_FROM_LARGE">
    <locale language="en">The start 'From' date must not be in the future.</locale>
  </message>
  <message name="ERR_BPOCASESEARCH_FV_START_DATE_TO_LARGE">
    <locale language="en">The start 'To' date must not be in the future.</locale>
  </message>
  <message name="ERR_BPOCASESEARCH_XFV_START_DATE_FROM_START_DATE_TO">
    <locale language="en">The start 'To' date must not be before the start 'From' date.</locale>
  </message>
  <message name="ERR_BPOCASESEARCH_XFV_END_DATE_FROM_END_DATE_TO">
    <locale language="en">The end 'To' date must not be before the end 'From' date.</locale>
  </message>
  <message name="ERR_BPOCASESEARCH_XFV_START_DATE_FROM_END_DATE_FROM">
    <locale language="en">The end 'From' date must not be before the start 'From' date.</locale>
  </message>
  <message name="ERR_BPOCASESEARCH_XFV_START_DATE_TO_END_DATE_TO">
    <locale language="en">The end 'To' date must not be before the start 'To' date.</locale>
  </message>
  <message name="ERR_BPOCASESEARCH_XFV_STATUS_TYPE">
    <locale language="en">The status '%1c' is not valid for the selected case type(s).</locale>
  </message>
  <message name="ERR_BPOCASESEARCH_FV_OWNER_EMPTY">
    <locale language="en">Please specify a case owner.</locale>
  </message>
  <message name="INF_BPOCASESEARCH_LAST_TRANSACTION">
    <locale language="en">%1s - %2d</locale>
  </message>
  <message name="INF_BPOCASESEARCH_CASE_NOT_SEARCHABLE">
    <locale language="en">The case reference number entered is a valid reference but not for searching on cases listed on this page.</locale>
  </message>
  <message name="ERR_BPOCASESEARCH_FV_INVESTIGATION_OWNER_EMPTY">
    <locale language="en">Please specify an investigation owner.</locale>
  </message>
  <message name="ERR_BPOCASESEARCH_INVESTIGATION_SEARCH_UNIMPLEMENTED">
    <locale language="en">No Investigation Search implemented. Please contact an Administrator.</locale>
  </message>
  <message name="INF_BPOCASESEARCH_INVESTIGATION_NO_MATCH">
    <locale language="en">No investigation could be found which matched the search criteria.</locale>
  </message>
  <!-- BEGIN, CR00327929, ZV -->
  <message name="INF_BPOCASESEARCH_CASE_SEARCH_CRITERIA_TEXT_TYPE_OWNER_STATUS">
    <locale language="en">Cases for types(s) %1s owned by %2s with a status of %3s.</locale>
  </message>
  <message name="INF_BPOCASESEARCH_CASE_SEARCH_CRITERIA_TEXT_OWNER">
    <locale language="en">Cases owned by %1s.</locale>
  </message>
  <message name="INF_BPOCASESEARCH_CASE_SEARCH_CRITERIA_TEXT_OWNER_STATUS">
    <locale language="en">Cases owned by %1s with a status of %2s.</locale>
  </message>
  <message name="INF_BPOCASESEARCH_CASE_SEARCH_CRITERIA_TEXT_TYPE_OWNER">
    <locale language="en">Cases for types(s) %1s owned by %2s.</locale>
  </message>
  <message name="INF_BPOCASESEARCH_CASE_SEARCH_CRITERIA_TEXT_ALL_TYPES_OWNER_STATUS">
    <locale language="en">Cases for all types owned by %1s with a status of %2s.</locale>
  </message>
  <message name="INF_BPOCASESEARCH_CASE_SEARCH_CRITERIA_TEXT_ALL_TYPES_OWNER">
    <locale language="en">Cases for all types owned by %1s.</locale>
  </message>
  <message name="INF_BPOCASESEARCH_INVESTIGATION_SEARCH_CRITERIA_TEXT_TYPE_OWNER_STATUS">
    <locale language="en">Investigations for types(s) %1s owned by %2s with a status of %3s.</locale>
  </message>
  <message name="INF_BPOCASESEARCH_INVESTIGATION_SEARCH_CRITERIA_TEXT_OWNER">
    <locale language="en">Investigations owned by %1s.</locale>
  </message>
  <message name="INF_BPOCASESEARCH_INVESTIGATION_SEARCH_CRITERIA_TEXT_OWNER_STATUS">
    <locale language="en">Investigations owned by %1s with a status of %2s.</locale>
  </message>
  <message name="INF_BPOCASESEARCH_INVESTIGATION_SEARCH_CRITERIA_TEXT_TYPE_OWNER">
    <locale language="en">Investigations for types(s) %1s owned by %2s.</locale>
  </message>
  <message name="INF_BPOCASESEARCH_INVESTIGATION_SEARCH_CRITERIA_TEXT_ALL_TYPES_OWNER_STATUS">
    <locale language="en">Investigations for all types owned by %1s with a status of %2s.</locale>
  </message>
  <message name="INF_BPOCASESEARCH_INVESTIGATION_SEARCH_CRITERIA_TEXT_ALL_TYPES_OWNER">
    <locale language="en">Investigations for all types owned by %1s.</locale>
  </message>
  <!-- END, CR00327929 -->
</messages>
