<?xml version="1.0" encoding="UTF-8"?>
<!--
  Licensed Materials - Property of IBM
 
  Copyright IBM Corporation 2012. All Rights Reserved.

  US Government Users Restricted Rights - Use, duplication or disclosure 
  restricted by GSA ADP Schedule Contract with IBM Corp.
-->
<!-- 
Copyright 2003-2005 Curam Software Ltd.
All rights reserved.

This software is the confidential and proprietary information of Curam
Software, Ltd. ("Confidential Information").  You shall not
disclose such Confidential Information and shall use it only in accordance
with the terms of the license agreement you entered into with Curam Software.
-->
<messages package="curam.message">
  <message name="ERR_SERVICESUPPLIER_FV_CLOSED">
    <locale language="en">"%1s" is no longer an active service supplier.</locale>
  </message>
  <message name="ERR_SUPPLIERRETURNHEADER_DUPLICATE_HEADER_INFO">
    <locale language="en">A return exists for %1s, with the same details. Please, check the return is not a duplicate.</locale>
  </message>
  <message name="ERR_SUPPLIERRETURNHEADER_FV_LINEITEMS">
    <locale language="en">The number of line items entered on the header does not match the number of line items associated with this return.</locale>
  </message>
  <message name="ERR_SUPPLIERRETURNHEADER_FV_TOTALAMOUNT">
    <locale language="en">The total amount of the return entered on the header does not match the sum of the amounts of each of the line items associated with this return.</locale>
  </message>
  <message name="ERR_SUPPLIERRETURNHEADER_XFV_RECEIPTDATE">
    <locale language="en">The date of a service on a return line item may not be greater than the receipt date of the return. Line item(s) with services on the following date(s) are invalid: %1s.</locale>
  </message>
  <message name="ERR_SUPPLIERRETURNHEADER_INVALID_NOREF">
    <locale language="en">The following errors occurred during validation of the supplier return: %1s.</locale>
  </message>
  <message name="ERR_SUPPLIERRETURNHEADER_INVALID">
    <locale language="en">The following errors occurred during validation of the supplier return with reference number %1s: %2s.</locale>
  </message>
  <message name="INF_SUPPLIERRETURNHEADER_VALID">
    <locale language="en">The supplier return is valid.</locale>
  </message>
  <message name="INF_SUPPLIERRETURNS_PROCESSING">
    <locale language="en">Your request for processing of this return has been queued for processing.</locale>
  </message>
  <message name="INF_SUPPLIERRETURNS_PRODUCT_ORDERS">
    <locale language="en">No products on the system support orders.</locale>
  </message>
  <message name="ERR_SUPPLIERRETURNLINEITEM_CONCERN_BANKACCOUNT">
    <locale language="en">The default payment method for %1s is EFT. The following clients do not have bank accounts registered: %2s</locale>
  </message>
  <message name="ERR_METHOD_OF_ENTRY_MODIFIED">
    <locale language="en">The method of entry must not be modified.</locale>
  </message>
  <message name="ERR_STATUS_CODE_MODIFIED">
    <locale language="en">The supplier return status code must not be modified.</locale>
  </message>
</messages>