<?xml version="1.0" encoding="UTF-8"?>
<!--
  Licensed Materials - Property of IBM
 
  Copyright IBM Corporation 2012. All Rights Reserved.

  US Government Users Restricted Rights - Use, duplication or disclosure 
  restricted by GSA ADP Schedule Contract with IBM Corp.
-->
<!-- 
Copyright (c) 2005-2011 Curam Software Ltd.
All rights reserved.

This software is the confidential and proprietary information of Curam
Software, Ltd. ("Confidential Information").  You shall not
disclose such Confidential Information and shall use it only in accordance
with the terms of the license agreement you entered into with Curam Software.
-->
<messages package="curam.message">
  <message name="INF_TASK_HISTORY_TIME_WORKED_CHANGED">
    <locale language="en">Time worked changed on %1z %2s by %3s.  \nChanged From: %4s.  \nChanged To: %5s.  \n%6s</locale>
  </message>
  <message name="INF_TASK_HISTORY_CREATED">
    <locale language="en">Task created on %1z %2s by %3s.  \n%4s</locale>
  </message>
  <message name="INF_TASK_HISTORY_UNRESERVED">
    <locale language="en">Task made available on %1z %2s by %3s.  \nMade Available From: %4s.  \n%5s</locale>
  </message>
  <message name="INF_TASK_HISTORY_COMMENT">
    <locale language="en">Comment added on %1z %2s by %3s.  \n%4s</locale>
  </message>
  <message name="INF_TASK_HISTORY_RESERVED_WITH_RESERVEDTO">
    <locale language="en">Task added to My Tasks list on %1z %2s by %3s.  \nTaken from the My Tasks list of: %4s.  \nAdded to the My Tasks list of: %5s.  \n%6s</locale>
  </message>
  <!-- BEGIN, CR00021458, SP-->
  <message name="INF_TASK_HISTORY_RESERVED_WITHOUT_RESERVEDTO">
    <locale language="en">Task added to the My Tasks list on %1z %2s by %3s.  \nTaken from the My Tasks list of: %4s.  \n%5s</locale>
  </message>
  <message name="INF_TASK_HISTORY_RESERVED_WITHOUT_RESERVEDFROM">
    <locale language="en">Task added to the My Tasks list on %1z %2s by %3s.  \nAdded to the My Tasks list of: %4s.  \n%5s</locale>
  </message>
  <!-- END, CR00021458 -->
  <message name="INF_TASK_HISTORY_FORWARDED">
    <locale language="en">Task forwarded on %1z %2s by %3s.  \nForwarded From: %4s.  \nForwarded To: %5s.  \n%6s</locale>
  </message>
  <message name="INF_TASK_HISTORY_REALLOCATED">
    <locale language="en">Task reallocated on %1z %2s by %3s.  \nReallocated From: %4s.  \n%5s</locale>
  </message>
  <message name="INF_TASK_HISTORY_DEFERRED">
    <locale language="en">Task deferred on %1z %2s by %3s.  \nDeferred Until: %4s.  \n%5s</locale>
  </message>
  <message name="INF_TASK_HISTORY_DEFERRED_WITH_DATE_SPECIFIED">
    <locale language="en">Task deferred on %1z %2s by %3s.  \nDeferred Until: %4d.  \n%5s</locale>
  </message>
  <message name="INF_TASK_HISTORY_DEFERRED_WITH_NO_DATE_SPECIFIED">
    <locale language="en">Task deferred on %1z %2s by %3s.  \nDeferred Until: No Date Specified.  \n%4s</locale>
  </message>
  <message name="INF_TASK_HISTORY_RESTARTED">
    <locale language="en">Task restarted on %1z %2s by %3s.  \n%4s</locale>
  </message>
  <message name="INF_TASK_HISTORY_ALLOCATED_USING_FAILURE_ALLOCATION_STRATEGY">
    <locale language="en">Task allocated using the failure allocation strategy named %1s.</locale>
  </message>
  <message name="INF_TASK_HISTORY_ALLOCATED_TO_DEFAULT_WORK_QUEUE">
    <locale language="en">Task assigned to the default work queue named %1s.</locale>
  </message>
  <message name="INF_TASK_HISTORY_CLOSED">
    <locale language="en">Task closed on %1z %2s by %3s</locale>
  </message>
  <message name="INF_TASK_HISTORY_DEADLINE_EXPIRED">
    <locale language="en">Task deadline expired on %1z %2s</locale>
  </message>
  <message name="INF_TASK_HISTORY_DEADLINE_MODIFIED">
    <locale language="en">Task deadline modified from %1s to %2s on %3z %4s by %5s.  \n%6s</locale>
  </message>
  <message name="INF_TASK_HISTORY_DEADLINE_UPDATED">
    <locale language="en">Task deadline modified from %1z to %2z on %3z %4s by %5s.  \n%6s</locale>
  </message>
  <message name="INF_TASK_HISTORY_PRIORITY_MODIFIED">
    <locale language="en">Task priority modified from %1s to %2s on %3z %4s by %5s.  \n%6s</locale>
  </message>
  <message name="INF_TASK_AUTOMATICALLY_ADD_TO_USER_TASKS">
    <locale language="en">Task automatically added to the task list of User %1s on %2z %3s by %4s</locale>
  </message>
  <message name="INF_TASK_HISTORY_HEADER">
    <locale language="en">\n</locale>
  </message>
  <message name="INF_TASK_HISTORY_FOOTER">
    <locale language="en">\n-------------------------------------</locale>
  </message>
</messages>
