<?xml version="1.0" encoding="UTF-8"?>

<!--
  Licensed Materials - Property of IBM
 
  Copyright IBM Corporation 2012. All Rights Reserved.

  US Government Users Restricted Rights - Use, duplication or disclosure 
  restricted by GSA ADP Schedule Contract with IBM Corp.
-->
<!--
Copyright 2005 Curam Software Ltd.
All rights reserved.
This software is the confidential and proprietary information of Curam
Software, Ltd. ("Confidential Information").  You shall not
disclose such Confidential Information and shall use it only in accordance
with the terms of the license agreement you entered into with Curam Software.
-->
<messages package="curam.message"> 
  <message name="ERR_SAMPLESPORTINGACTIVITYEXPENSE_XRV_TOTALAMOUNT_SPORTINGACTIVITYPAYMENTAMOUNT"> 
    <locale language="fr">Le montant total de toutes les dépenses liées aux exemples d'activité sportive doit être inférieur ou égal au montant du paiement des exemples d'activité sportive.</locale> 
  </message>  
  <message name="ERR_SAMPLESPORTINGACTIVITYEXPENSE_XRV_SPORTINGACTIVITY_MISSING"> 
    <locale language="fr">Cet enregistrement de dépenses liées à l'activité sportive doit être associé à un enregistrement d'activité sportive.</locale> 
  </message>  
  <message name="ERR_SAMPLESPORTINGACTIVITYEXPENSE_XRV_SPORTINGACTIVITY_EXISTS"> 
    <locale language="fr">Un ou plusieurs enregistrements de dépenses liées à une activité sportive de type %1s se chevauchant ont été découverts pour %2s.</locale> 
  </message> 
</messages>
