<?xml version="1.0" encoding="UTF-8"?>
<!--
  Licensed Materials - Property of IBM
  
  Copyright IBM Corporation 2012. All Rights Reserved.
 
  US Government Users Restricted Rights - Use, duplication or disclosure 
  restricted by GSA ADP Schedule Contract with IBM Corp.
-->
<messages package="curam.commonintake.message">
  <message name="ERR_FV_APPLICATION_CASE_MANDATORY">
    <locale language="en">An application case must be specified.</locale>
  </message>
  <message name="ERR_FV_AUTHORISATION_DATE_MANDATORY">
    <locale language="en" country="US">Authorization date must be specified.</locale>            
    <locale language="en">Authorization date must be specified.</locale>
  </message>
  <message name="ERR_FV_AUTHORISATION_USER_MANDATORY">
    <locale language="en" country="US">Authorization user must be specified.</locale>                
    <locale language="en">Authorization user must be specified.</locale>
  </message>
  <message name="ERR_FV_PROGRAM_MANDATORY">
    <locale language="en">Program must be specified.</locale>
  </message>
</messages>
